dogclient/__init__.py
dogclient/client.py
dogclient/events.py
dogclient-0.0.2.dist-info/LICENCE.txt
dogclient-0.0.2.dist-info/METADATA
dogclient-0.0.2.dist-info/WHEEL
dogclient-0.0.2.dist-info/top_level.txt
dogclient-0.0.2.dist-info/RECORD
